scapy_usbbluetooth/__init__.py
scapy_usbbluetooth/usbbluetooth_socket.py
scapy_usbbluetooth-0.1.1.dist-info/METADATA
scapy_usbbluetooth-0.1.1.dist-info/WHEEL
scapy_usbbluetooth-0.1.1.dist-info/licenses/LICENSE.md
scapy_usbbluetooth-0.1.1.dist-info/RECORD
