Metadata-Version: 2.4
Name: scapy-usbbluetooth
Version: 0.1.1
Summary: Scapy helpers to communicate with Bluetooth controllers
Project-URL: Homepage, https://github.com/usbbluetooth/scapy-usbbluetooth
Project-URL: Bug Tracker, https://github.com/usbbluetooth/scapy-usbbluetooth/issues
Author-email: Antonio Vázquez Blanco <antoniovazquezblanco@gmail.com>
License: GPL-3.0-only
License-File: LICENSE.md
Keywords: bluetooth
Classifier: Intended Audience :: Developers
Classifier: Intended Audience :: Information Technology
Classifier: Intended Audience :: Science/Research
Classifier: Intended Audience :: System Administrators
Classifier: Intended Audience :: Telecommunications Industry
Classifier: License :: OSI Approved :: GNU General Public License v3 (GPLv3)
Classifier: Operating System :: OS Independent
Classifier: Programming Language :: Python :: 3
Classifier: Topic :: Security
Requires-Python: >=3.0
Requires-Dist: scapy
Requires-Dist: usbbluetooth>=0.1.0
